rfcx/__init__.py
rfcx/_api_auth.py
rfcx/_api_rfcx.py
rfcx/_audio.py
rfcx/_authentication.py
rfcx/_classifiers.py
rfcx/_credentials.py
rfcx/_helper.py
rfcx/_ingest.py
rfcx/_pkce.py
rfcx/_util.py
rfcx/client.py
rfcx-0.3.1.dist-info/METADATA
rfcx-0.3.1.dist-info/WHEEL
rfcx-0.3.1.dist-info/top_level.txt
rfcx-0.3.1.dist-info/RECORD
