Metadata-Version: 2.1
Name: rfcx
Version: 0.3.1
Summary: Client SDK for the Rainforest Connection and Arbimon platforms
Home-page: https://github.com/rfcx/rfcx-sdk-python
Author: Rainforest Connection
Author-email: antony@rfcx.org
License: None
Platform: UNKNOWN
Classifier: Development Status :: 1 - Planning
Classifier: Intended Audience :: Science/Research
Classifier: Programming Language :: Python :: 3
Classifier: Operating System :: OS Independent
Requires-Dist: httplib2
Requires-Dist: six
Requires-Dist: requests
Requires-Dist: requests-toolbelt
